ailoos/__init__.py
ailoos/automated_testing_demo.py
ailoos/conftest.py
ailoos/demo_complete_pipeline.py
ailoos/demo_complete_system.py
ailoos/demo_corrective_rag.py
ailoos/demo_feedback_loops.py
ailoos/demo_self_rag.py
ailoos/demo_speculative_rag.py
ailoos/rag_demo.py
ailoos/ai/__init__.py
ailoos/ai/personalization.py
ailoos/api/__init__.py
ailoos/api/analytics_api.py
ailoos/api/compliance_api.py
ailoos/api/dashboard_api.py
ailoos/api/datahub_api.py
ailoos/api/dependencies.py
ailoos/api/empoorio_api.py
ailoos/api/federated_api.py
ailoos/api/gateway.py
ailoos/api/main.py
ailoos/api/marketplace_api.py
ailoos/api/models_api.py
ailoos/api/rag_api.py
ailoos/api/rate_limiting.py
ailoos/api/settings_api.py
ailoos/api/system_tools_api.py
ailoos/api/technical_dashboard_api.py
ailoos/api/wallet_api.py
ailoos/auditing/__init__.py
ailoos/auditing/advanced_audit_logging.py
ailoos/auditing/api_endpoints.py
ailoos/auditing/audit_compliance.py
ailoos/auditing/audit_event.py
ailoos/auditing/audit_logger.py
ailoos/auditing/audit_manager.py
ailoos/auditing/audit_monitoring.py
ailoos/auditing/audit_query_api.py
ailoos/auditing/audit_query_engine.py
ailoos/auditing/audit_retention.py
ailoos/auditing/audit_smart_contracts.py
ailoos/auditing/audit_storage.py
ailoos/auditing/blockchain_audit_integration.py
ailoos/auditing/blockchain_auditor.py
ailoos/auditing/compliance_reporter.py
ailoos/auditing/dashboard.py
ailoos/auditing/hash_chain_manager.py
ailoos/auditing/immutable_log_storage.py
ailoos/auditing/integration.py
ailoos/auditing/metrics_collector.py
ailoos/auditing/oracle_auditor.py
ailoos/auditing/privacy_auditor.py
ailoos/auditing/realtime_monitor.py
ailoos/auditing/security_monitor.py
ailoos/auditing/structured_logger.py
ailoos/auditing/test_blockchain_audit_system.py
ailoos/auditing/websocket_endpoints.py
ailoos/auditing/zk_audit_logger.py
ailoos/auditing/zk_auditor.py
ailoos/automated_testing/__init__.py
ailoos/automated_testing/e2e_test_runner.py
ailoos-2.4.0.dist-info/licenses/LICENSE
ailoos-2.4.0.dist-info/METADATA
ailoos-2.4.0.dist-info/WHEEL
ailoos-2.4.0.dist-info/entry_points.txt
ailoos-2.4.0.dist-info/top_level.txt
ailoos-2.4.0.dist-info/RECORD
