Metadata-Version: 2.4
Name: ailoos
Version: 2.4.0
Summary: Unified SDK experience for computer nodes only
Home-page: https://github.com/empoorio/ailoos
Author: Empoorio
Author-email: dev@empoorio.com
License: Proprietary - Ailoos Technologies & Empoorio Ecosystem
Project-URL: Bug Tracker, https://github.com/empoorio/ailoos/issues
Project-URL: Documentation, https://ailoos.dev/docs
Project-URL: Source Code, https://github.com/empoorio/ailoos
Project-URL: Discord, https://discord.gg/ailoos
Project-URL: PyPI, https://pypi.org/project/ailoos/
Project-URL: Dashboard Demo, https://dashboard.ailoos.dev
Keywords: ai,machine-learning,federated-learning,decentralized,blockchain,wallet,staking,defi,dashboard,web-ui,websocket,empoorio,sovereign-ai,dracma,interactive-dashboard
Platform: any
Classifier: Development Status :: 4 - Beta
Classifier: Intended Audience :: Developers
Classifier: Intended Audience :: Science/Research
Classifier: License :: Other/Proprietary License
Classifier: Operating System :: OS Independent
Classifier: Programming Language :: Python :: 3
Classifier: Programming Language :: Python :: 3.8
Classifier: Programming Language :: Python :: 3.9
Classifier: Programming Language :: Python :: 3.10
Classifier: Programming Language :: Python :: 3.11
Classifier: Topic :: Scientific/Engineering :: Artificial Intelligence
Classifier: Topic :: Software Development :: Libraries :: Python Modules
Classifier: Topic :: System :: Distributed Computing
Classifier: Topic :: Office/Business :: Financial :: Investment
Classifier: Topic :: Security :: Cryptography
License-File: LICENSE
Requires-Dist: aiohttp>=3.8.0
Requires-Dist: psutil>=5.9.0
Requires-Dist: numpy>=1.21.0
Requires-Dist: pyyaml>=6.0
Requires-Dist: requests>=2.28.0
Requires-Dist: tqdm>=4.64.0
Requires-Dist: structlog>=21.1.0
Requires-Dist: tenseal>=0.3.0
Requires-Dist: torch>=2.0.0
Requires-Dist: transformers>=4.30.0
Requires-Dist: pandas>=2.0.0
Requires-Dist: fastapi>=0.104.0
Requires-Dist: uvicorn[standard]>=0.24.0
Requires-Dist: websockets>=12.0
Requires-Dist: pydantic>=2.0.0
Requires-Dist: rich>=13.0.0
Requires-Dist: questionary>=2.0.0
Requires-Dist: cryptography>=41.0.0
Requires-Dist: PyJWT>=2.0.0
Requires-Dist: passlib[bcrypt]>=1.7.0
Requires-Dist: nest_asyncio>=1.5.0
Provides-Extra: dev
Requires-Dist: pytest>=7.0.0; extra == "dev"
Requires-Dist: pytest-asyncio>=0.21.0; extra == "dev"
Requires-Dist: black>=22.0.0; extra == "dev"
Requires-Dist: isort>=5.10.0; extra == "dev"
Requires-Dist: flake8>=4.0.0; extra == "dev"
Requires-Dist: mypy>=0.950; extra == "dev"
Requires-Dist: sphinx>=5.0.0; extra == "dev"
Requires-Dist: sphinx-rtd-theme>=1.0.0; extra == "dev"
Provides-Extra: gpu
Requires-Dist: torch>=2.0.0; extra == "gpu"
Requires-Dist: torchvision>=0.15.0; extra == "gpu"
Requires-Dist: torchaudio>=2.0.0; extra == "gpu"
Provides-Extra: ai
Requires-Dist: transformers>=4.21.0; extra == "ai"
Requires-Dist: accelerate>=0.12.0; extra == "ai"
Requires-Dist: datasets>=2.4.0; extra == "ai"
Provides-Extra: dashboard
Requires-Dist: fastapi>=0.104.0; extra == "dashboard"
Requires-Dist: uvicorn[standard]>=0.24.0; extra == "dashboard"
Requires-Dist: websockets>=12.0; extra == "dashboard"
Requires-Dist: pydantic>=2.0.0; extra == "dashboard"
Provides-Extra: full
Requires-Dist: torch>=2.0.0; extra == "full"
Requires-Dist: torchvision>=0.15.0; extra == "full"
Requires-Dist: torchaudio>=2.0.0; extra == "full"
Requires-Dist: transformers>=4.21.0; extra == "full"
Requires-Dist: datasets>=2.4.0; extra == "full"
Requires-Dist: accelerate>=0.12.0; extra == "full"
Requires-Dist: pandas>=1.5.0; extra == "full"
Requires-Dist: matplotlib>=3.5.0; extra == "full"
Requires-Dist: seaborn>=0.11.0; extra == "full"
Requires-Dist: scikit-learn>=1.1.0; extra == "full"
Requires-Dist: fastapi>=0.104.0; extra == "full"
Requires-Dist: uvicorn[standard]>=0.24.0; extra == "full"
Requires-Dist: websockets>=12.0; extra == "full"
Requires-Dist: pydantic>=2.0.0; extra == "full"
Provides-Extra: blockchain
Requires-Dist: cryptography>=41.0.0; extra == "blockchain"
Provides-Extra: bridge
Requires-Dist: requests>=2.28.0; extra == "bridge"
Requires-Dist: urllib3>=1.26.0; extra == "bridge"
Provides-Extra: lite
Dynamic: author
Dynamic: author-email
Dynamic: classifier
Dynamic: description
Dynamic: description-content-type
Dynamic: home-page
Dynamic: keywords
Dynamic: license
Dynamic: license-file
Dynamic: platform
Dynamic: project-url
Dynamic: provides-extra
Dynamic: requires-dist
Dynamic: summary
